README.txt
setup.cfg
setup.py
collective/__init__.py
collective.smartkeywordmanager.egg-info/PKG-INFO
collective.smartkeywordmanager.egg-info/SOURCES.txt
collective.smartkeywordmanager.egg-info/dependency_links.txt
collective.smartkeywordmanager.egg-info/entry_points.txt
collective.smartkeywordmanager.egg-info/namespace_packages.txt
collective.smartkeywordmanager.egg-info/not-zip-safe
collective.smartkeywordmanager.egg-info/paster_plugins.txt
collective.smartkeywordmanager.egg-info/requires.txt
collective.smartkeywordmanager.egg-info/top_level.txt
collective/smartkeywordmanager/__init__.py
collective/smartkeywordmanager/configure.zcml
collective/smartkeywordmanager/smart_keyword_edit_form.pt
collective/smartkeywordmanager/tests.py
collective/smartkeywordmanager/views.py
collective/smartkeywordmanager/profiles/default/actions.xml
collective/smartkeywordmanager/profiles/default/metadata.xml
collective/smartkeywordmanager/profiles/default/registry.xml
docs/HISTORY.txt
docs/INSTALL.txt
docs/LICENSE.GPL
docs/LICENSE.txt