Metadata-Version: 1.0
Name: collective.smartkeywordmanager
Version: 0.6
Summary: Used to apply tags to objects in a collection.
Home-page: http://svn.plone.org/svn/collective/
Author: Four Digits, maartenkling
Author-email: info@fourdigits.nl
License: GPL
Platform: UNKNOWN
Classifier: Framework :: Plone
Classifier: Programming Language :: Python
